easyclimate_map/__init__.py
easyclimate_map/map_tibetan_plateau.py
easyclimate_map/map_zh_CN.py
easyclimate_map/tool.py
easyclimate_map/version.py
easyclimate_map/shpdata/tibetan_plateau/TP_basins.7z
easyclimate_map/shpdata/zh_CN/administration_1st/res1_4m.7z
easyclimate_map/shpdata/zh_CN/administration_2nd/res2_4m.7z
easyclimate_map/shpdata/zh_CN/nation/bou1_4l.7z
easyclimate_map/shpdata/zh_CN/nation/bou1_4p.7z
easyclimate_map/shpdata/zh_CN/provinces/bou2_4l.7z
easyclimate_map/shpdata/zh_CN/provinces/bou2_4p.7z
easyclimate_map/shpdata/zh_CN/river1/hyd1_4l.7z
easyclimate_map/shpdata/zh_CN/river1/hyd1_4p.7z
easyclimate_map/shpdata/zh_CN/river3/hyd2_4l.7z
easyclimate_map/shpdata/zh_CN/river3/hyd2_4p.7z
easyclimate_map-2026.1.0.dist-info/licenses/LICENSE
easyclimate_map-2026.1.0.dist-info/METADATA
easyclimate_map-2026.1.0.dist-info/WHEEL
easyclimate_map-2026.1.0.dist-info/top_level.txt
easyclimate_map-2026.1.0.dist-info/RECORD
