Metadata-Version: 2.4
Name: easyclimate_map
Version: 2026.1.0
Summary: Easily obtain map data
Author-email: shenyulu <shenyulu2020@gmail.com>
License: BSD 3-Clause License
Project-URL: homepage, https://github.com/shenyulu/easyclimate-map
Project-URL: documentation, https://easyclimate-map.readthedocs.io/en/latest/
Project-URL: source, https://github.com/shenyulu/easyclimate-map
Project-URL: download, https://pypi.org/project/easyclimate-map/#files
Project-URL: tracker, https://github.com/shenyulu/easyclimate-map/issues
Keywords: climate,atmosphere,weather,meteorology
Classifier: Programming Language :: Python :: 3.10
Classifier: Programming Language :: Python :: 3.11
Classifier: Programming Language :: Python :: 3.12
Classifier: Programming Language :: Python :: 3.13
Classifier: Programming Language :: Python :: 3 :: Only
Classifier: Topic :: Scientific/Engineering
Classifier: Operating System :: Microsoft :: Windows
Classifier: Operating System :: POSIX
Classifier: Operating System :: Unix
Classifier: Operating System :: MacOS
Requires-Python: >=3.10
License-File: LICENSE
Requires-Dist: geopandas
Requires-Dist: py7zr
Requires-Dist: rich
Dynamic: license-file
